<?xml version="1.0" encoding="UTF-8"?>
<xml xmlns="http://www.w3.org/1999/xhtml">
  <block type="factory_base" id="KeFSz*cyn|W)k[5BRqYC" deletable="false" movable="false" x="0" y="0">
    <mutation connections="LEFT" />
    <field name="NAME">data_block</field>
    <field name="INLINE">AUTO</field>
    <field name="CONNECTIONS">LEFT</field>
    <statement name="INPUTS">
      <block type="input_dummy" id=":JDy?V3Yb/2MR+Y_0q],">
        <field name="ALIGN">LEFT</field>
        <statement name="FIELDS">
          <block type="field_static" id="5s#r`;Xy@nI5;Feb,I[Y">
            <field name="TEXT">block</field>
            <next>
              <block type="field_dropdown" id="pfx+fm,![}(*DwJ#52eM">
                <mutation options="198" />
                <field name="FIELDNAME">VALUE</field>
                <field name="USER0">Air</field>
<field name="CPU0">0</field>
<field name="USER1">Stone</field>
<field name="CPU1">1</field>
<field name="USER2">Grass Block</field>
<field name="CPU2">2</field>
<field name="USER3">Dirt</field>
<field name="CPU3">3</field>
<field name="USER4">Cobblestone</field>
<field name="CPU4">4</field>
<field name="USER5">Wood Planks</field>
<field name="CPU5">5</field>
<field name="USER6">Sapling</field>
<field name="CPU6">6</field>
<field name="USER7">Bedrock</field>
<field name="CPU7">7</field>
<field name="USER8">Water</field>
<field name="CPU8">8</field>
<field name="USER9">Stationary Water</field>
<field name="CPU9">9</field>
<field name="USER10">Lava</field>
<field name="CPU10">10</field>
<field name="USER11">Stationary Lava</field>
<field name="CPU11">11</field>
<field name="USER12">Sand</field>
<field name="CPU12">12</field>
<field name="USER13">Gravel</field>
<field name="CPU13">13</field>
<field name="USER14">Gold Ore</field>
<field name="CPU14">14</field>
<field name="USER15">Iron Ore</field>
<field name="CPU15">15</field>
<field name="USER16">Coal Ore</field>
<field name="CPU16">16</field>
<field name="USER17">Wood</field>
<field name="CPU17">17</field>
<field name="USER18">Leaves</field>
<field name="CPU18">18</field>
<field name="USER19">Sponge</field>
<field name="CPU19">19</field>
<field name="USER20">Glass</field>
<field name="CPU20">20</field>
<field name="USER21">Lapis Lazuli Ore</field>
<field name="CPU21">21</field>
<field name="USER22">Lapis Lazuli Block</field>
<field name="CPU22">22</field>
<field name="USER23">Dispenser</field>
<field name="CPU23">23</field>
<field name="USER24">Sandstone</field>
<field name="CPU24">24</field>
<field name="USER25">Note Block</field>
<field name="CPU25">25</field>
<field name="USER26">Bed</field>
<field name="CPU26">26</field>
<field name="USER27">Powered Rail</field>
<field name="CPU27">27</field>
<field name="USER28">Detector Rail</field>
<field name="CPU28">28</field>
<field name="USER29">Sticky Piston</field>
<field name="CPU29">29</field>
<field name="USER30">Cobweb</field>
<field name="CPU30">30</field>
<field name="USER31">Grass</field>
<field name="CPU31">31</field>
<field name="USER32">Dead Bush</field>
<field name="CPU32">32</field>
<field name="USER33">Piston</field>
<field name="CPU33">33</field>
<field name="USER34">Piston Head</field>
<field name="CPU34">34</field>
<field name="USER35">Wool</field>
<field name="CPU35">35</field>
<field name="USER36">Block moved by Piston</field>
<field name="CPU36">36</field>
<field name="USER37">Dandelion</field>
<field name="CPU37">37</field>
<field name="USER38">Poppy</field>
<field name="CPU38">38</field>
<field name="USER39">Brown Mushroom</field>
<field name="CPU39">39</field>
<field name="USER40">Red Mushroom</field>
<field name="CPU40">40</field>
<field name="USER41">Block of Gold</field>
<field name="CPU41">41</field>
<field name="USER42">Block of Iron</field>
<field name="CPU42">42</field>
<field name="USER43">Double Stone Slab</field>
<field name="CPU43">43</field>
<field name="USER44">Stone Slab</field>
<field name="CPU44">44</field>
<field name="USER45">Bricks</field>
<field name="CPU45">45</field>
<field name="USER46">TNT</field>
<field name="CPU46">46</field>
<field name="USER47">Bookshelf</field>
<field name="CPU47">47</field>
<field name="USER48">Moss Stone</field>
<field name="CPU48">48</field>
<field name="USER49">Obsidian</field>
<field name="CPU49">49</field>
<field name="USER50">Torch</field>
<field name="CPU50">50</field>
<field name="USER51">Fire</field>
<field name="CPU51">51</field>
<field name="USER52">Monster Spawner</field>
<field name="CPU52">52</field>
<field name="USER53">Oak Wood Stairs</field>
<field name="CPU53">53</field>
<field name="USER54">Chest</field>
<field name="CPU54">54</field>
<field name="USER55">Redstone Wire</field>
<field name="CPU55">55</field>
<field name="USER56">Diamond Ore</field>
<field name="CPU56">56</field>
<field name="USER57">Block of Diamond</field>
<field name="CPU57">57</field>
<field name="USER58">Crafting Table</field>
<field name="CPU58">58</field>
<field name="USER59">Wheat</field>
<field name="CPU59">59</field>
<field name="USER60">Farmland</field>
<field name="CPU60">60</field>
<field name="USER61">Furnace</field>
<field name="CPU61">61</field>
<field name="USER62">Burning Furnace</field>
<field name="CPU62">62</field>
<field name="USER63">Standing Sign</field>
<field name="CPU63">63</field>
<field name="USER64">Oak Door</field>
<field name="CPU64">64</field>
<field name="USER65">Ladder</field>
<field name="CPU65">65</field>
<field name="USER66">Rail</field>
<field name="CPU66">66</field>
<field name="USER67">Cobblestone Stairs</field>
<field name="CPU67">67</field>
<field name="USER68">Wall Sign</field>
<field name="CPU68">68</field>
<field name="USER69">Lever</field>
<field name="CPU69">69</field>
<field name="USER70">Stone Pressure Plate</field>
<field name="CPU70">70</field>
<field name="USER71">Iron Door</field>
<field name="CPU71">71</field>
<field name="USER72">Wooden Pressure Plate</field>
<field name="CPU72">72</field>
<field name="USER73">Redstone Ore</field>
<field name="CPU73">73</field>
<field name="USER74">Glowing Redstone Ore</field>
<field name="CPU74">74</field>
<field name="USER75">Redstone Torch (inactive)</field>
<field name="CPU75">75</field>
<field name="USER76">Redstone Torch (active)</field>
<field name="CPU76">76</field>
<field name="USER77">Stone Button</field>
<field name="CPU77">77</field>
<field name="USER78">Snow (layer)</field>
<field name="CPU78">78</field>
<field name="USER79">Ice</field>
<field name="CPU79">79</field>
<field name="USER80">Snow</field>
<field name="CPU80">80</field>
<field name="USER81">Cactus</field>
<field name="CPU81">81</field>
<field name="USER82">Clay</field>
<field name="CPU82">82</field>
<field name="USER83">Sugar Cane</field>
<field name="CPU83">83</field>
<field name="USER84">Jukebox</field>
<field name="CPU84">84</field>
<field name="USER85">Fence</field>
<field name="CPU85">85</field>
<field name="USER86">Pumpkin</field>
<field name="CPU86">86</field>
<field name="USER87">Netherrack</field>
<field name="CPU87">87</field>
<field name="USER88">Soul Sand</field>
<field name="CPU88">88</field>
<field name="USER89">Glowstone</field>
<field name="CPU89">89</field>
<field name="USER90">Nether Portal</field>
<field name="CPU90">90</field>
<field name="USER91">Jack o'Lantern</field>
<field name="CPU91">91</field>
<field name="USER92">Cake</field>
<field name="CPU92">92</field>
<field name="USER93">Redstone Repeater (inactive)</field>
<field name="CPU93">93</field>
<field name="USER94">Redstone Repeater (active)</field>
<field name="CPU94">94</field>
<field name="USER95">Stained Glass</field>
<field name="CPU95">95</field>
<field name="USER96">Trapdoor</field>
<field name="CPU96">96</field>
<field name="USER97">Monster Egg</field>
<field name="CPU97">97</field>
<field name="USER98">Stone Bricks</field>
<field name="CPU98">98</field>
<field name="USER99">Brown Mushroom (block)</field>
<field name="CPU99">99</field>
<field name="USER100">Red Mushroom (block)</field>
<field name="CPU100">100</field>
<field name="USER101">Iron Bars</field>
<field name="CPU101">101</field>
<field name="USER102">Glass Pane</field>
<field name="CPU102">102</field>
<field name="USER103">Melon</field>
<field name="CPU103">103</field>
<field name="USER104">Pumpkin Stem</field>
<field name="CPU104">104</field>
<field name="USER105">Melon Stem</field>
<field name="CPU105">105</field>
<field name="USER106">Vines</field>
<field name="CPU106">106</field>
<field name="USER107">Fence Gate</field>
<field name="CPU107">107</field>
<field name="USER108">Brick Stairs</field>
<field name="CPU108">108</field>
<field name="USER109">Stone Brick Stairs</field>
<field name="CPU109">109</field>
<field name="USER110">Mycelium</field>
<field name="CPU110">110</field>
<field name="USER111">Lily Pad</field>
<field name="CPU111">111</field>
<field name="USER112">Nether Brick</field>
<field name="CPU112">112</field>
<field name="USER113">Nether Brick Fence</field>
<field name="CPU113">113</field>
<field name="USER114">Nether Brick Stairs</field>
<field name="CPU114">114</field>
<field name="USER115">Nether Wart</field>
<field name="CPU115">115</field>
<field name="USER116">Enchantment Table</field>
<field name="CPU116">116</field>
<field name="USER117">Brewing Stand</field>
<field name="CPU117">117</field>
<field name="USER118">Cauldron</field>
<field name="CPU118">118</field>
<field name="USER119">End Portal</field>
<field name="CPU119">119</field>
<field name="USER120">End Portal Block</field>
<field name="CPU120">120</field>
<field name="USER121">End Stone</field>
<field name="CPU121">121</field>
<field name="USER122">Dragon Egg</field>
<field name="CPU122">122</field>
<field name="USER123">Redstone Lamp (inactive)</field>
<field name="CPU123">123</field>
<field name="USER124">Redstone Lamp (active)</field>
<field name="CPU124">124</field>
<field name="USER125">Double Wooden Slab</field>
<field name="CPU125">125</field>
<field name="USER126">Wooden Slab</field>
<field name="CPU126">126</field>
<field name="USER127">Cocoa</field>
<field name="CPU127">127</field>
<field name="USER128">Sandstone Stairs</field>
<field name="CPU128">128</field>
<field name="USER129">Emerald Ore</field>
<field name="CPU129">129</field>
<field name="USER130">Ender Chest</field>
<field name="CPU130">130</field>
<field name="USER131">Tripwire Hook</field>
<field name="CPU131">131</field>
<field name="USER132">Tripwire</field>
<field name="CPU132">132</field>
<field name="USER133">Block of Emerald</field>
<field name="CPU133">133</field>
<field name="USER134">Spruce Wood Stairs</field>
<field name="CPU134">134</field>
<field name="USER135">Birch Wood Stairs</field>
<field name="CPU135">135</field>
<field name="USER136">Jungle Wood Stairs</field>
<field name="CPU136">136</field>
<field name="USER137">Command Block</field>
<field name="CPU137">137</field>
<field name="USER138">Beacon</field>
<field name="CPU138">138</field>
<field name="USER139">Cobblestone Wall</field>
<field name="CPU139">139</field>
<field name="USER140">Flower Pot</field>
<field name="CPU140">140</field>
<field name="USER141">Carrot</field>
<field name="CPU141">141</field>
<field name="USER142">Potato</field>
<field name="CPU142">142</field>
<field name="USER143">Wooden Button</field>
<field name="CPU143">143</field>
<field name="USER144">Mob head</field>
<field name="CPU144">144</field>
<field name="USER145">Anvil</field>
<field name="CPU145">145</field>
<field name="USER146">Trapped Chest</field>
<field name="CPU146">146</field>
<field name="USER147">Weighted Pressure Plate (Light)</field>
<field name="CPU147">147</field>
<field name="USER148">Weighted Pressure Plate (Heavy)</field>
<field name="CPU148">148</field>
<field name="USER149">Redstone Comparator</field>
<field name="CPU149">149</field>
<field name="USER150">Redstone Comparator (deprecated)</field>
<field name="CPU150">150</field>
<field name="USER151">Daylight Sensor</field>
<field name="CPU151">151</field>
<field name="USER152">Block of Redstone</field>
<field name="CPU152">152</field>
<field name="USER153">Nether Quartz Ore</field>
<field name="CPU153">153</field>
<field name="USER154">Hopper</field>
<field name="CPU154">154</field>
<field name="USER155">Block of Quartz</field>
<field name="CPU155">155</field>
<field name="USER156">Quartz Stairs</field>
<field name="CPU156">156</field>
<field name="USER157">Activator Rail</field>
<field name="CPU157">157</field>
<field name="USER158">Dropper</field>
<field name="CPU158">158</field>
<field name="USER159">Stained Clay</field>
<field name="CPU159">159</field>
<field name="USER160">Stained Glass Pane</field>
<field name="CPU160">160</field>
<field name="USER161">Leaves (Acacia/Dark Oak)</field>
<field name="CPU161">161</field>
<field name="USER162">Wood (Acacia/Dark Oak)</field>
<field name="CPU162">162</field>
<field name="USER163">Acacia Wood Stairs</field>
<field name="CPU163">163</field>
<field name="USER164">Dark Oak Wood Stairs</field>
<field name="CPU164">164</field>
<field name="USER165">Slime Block</field>
<field name="CPU165">165</field>
<field name="USER166">Barrier</field>
<field name="CPU166">166</field>
<field name="USER167">Iron Trapdoor</field>
<field name="CPU167">167</field>
<field name="USER168">Prismarine</field>
<field name="CPU168">168</field>
<field name="USER169">Sea Lantern</field>
<field name="CPU169">169</field>
<field name="USER170">Hay Bale</field>
<field name="CPU170">170</field>
<field name="USER171">Carpet</field>
<field name="CPU171">171</field>
<field name="USER172">Hardened Clay</field>
<field name="CPU172">172</field>
<field name="USER173">Block of Coal</field>
<field name="CPU173">173</field>
<field name="USER174">Packed Ice</field>
<field name="CPU174">174</field>
<field name="USER175">Large Flowers</field>
<field name="CPU175">175</field>
<field name="USER176">Standing Banner</field>
<field name="CPU176">176</field>
<field name="USER177">Wall Banner</field>
<field name="CPU177">177</field>
<field name="USER178">Inverted Daylight Sensor</field>
<field name="CPU178">178</field>
<field name="USER179">Red Sandstone</field>
<field name="CPU179">179</field>
<field name="USER180">Red Sandstone Stairs</field>
<field name="CPU180">180</field>
<field name="USER181">Double Red Sandstone Slab</field>
<field name="CPU181">181</field>
<field name="USER182">Red Sandstone Slab</field>
<field name="CPU182">182</field>
<field name="USER183">Spruce Fence Gate</field>
<field name="CPU183">183</field>
<field name="USER184">Birch Fence Gate</field>
<field name="CPU184">184</field>
<field name="USER185">Jungle Fence Gate</field>
<field name="CPU185">185</field>
<field name="USER186">Dark Oak Fence Gate</field>
<field name="CPU186">186</field>
<field name="USER187">Acacia Fence Gate</field>
<field name="CPU187">187</field>
<field name="USER188">Spruce Fence</field>
<field name="CPU188">188</field>
<field name="USER189">Birch Fence</field>
<field name="CPU189">189</field>
<field name="USER190">Jungle Fence</field>
<field name="CPU190">190</field>
<field name="USER191">Dark Oak Fence</field>
<field name="CPU191">191</field>
<field name="USER192">Acacia Fence</field>
<field name="CPU192">192</field>
<field name="USER193">Spruce Door</field>
<field name="CPU193">193</field>
<field name="USER194">Birch Door</field>
<field name="CPU194">194</field>
<field name="USER195">Jungle Door</field>
<field name="CPU195">195</field>
<field name="USER196">Acacia Door</field>
<field name="CPU196">196</field>
<field name="USER197">Dark Oak Door</field>
<field name="CPU197">197</field>
              </block>
            </next>
          </block>
        </statement>
      </block>
    </statement>
    <value name="OUTPUTTYPE">
      <block type="type_number" id="ZBo46jJ3hxv(|xIg7aJ|" />
    </value>
  </block>
</xml>